s3pcmd.py
s3pcmd-0.1.2.data/scripts/s3pcmd.py
s3pcmd-0.1.2.dist-info/METADATA
s3pcmd-0.1.2.dist-info/WHEEL
s3pcmd-0.1.2.dist-info/entry_points.txt
s3pcmd-0.1.2.dist-info/top_level.txt
s3pcmd-0.1.2.dist-info/RECORD
